.flake8
.gitignore
LICENSE
MANIFEST.in
README.md
RELEASE_NOTES
pyproject.toml
setup.py
.github/workflows/test.yaml
esutil/__init__.py
esutil/algorithm.py
esutil/coords.py
esutil/cosmology_purepy.py
esutil/fits.py
esutil/hdfs.py
esutil/io.py
esutil/json_util.py
esutil/misc.py
esutil/numpy_util.py
esutil/oracle_util.py
esutil/ostools.py
esutil/pbar.py
esutil/plotting.py
esutil/random.py
esutil/sfile.py
esutil/sqlite_util.py
esutil/wcsutil.py
esutil/xmltools.py
esutil.egg-info/PKG-INFO
esutil.egg-info/SOURCES.txt
esutil.egg-info/dependency_links.txt
esutil.egg-info/requires.txt
esutil.egg-info/top_level.txt
esutil/cosmology/__init__.py
esutil/cosmology/_cosmolib.cpython-310-x86_64-linux-gnu.so
esutil/cosmology/_cosmolib.cpython-311-x86_64-linux-gnu.so
esutil/cosmology/_cosmolib.cpython-312-x86_64-linux-gnu.so
esutil/cosmology/cosmolib.c
esutil/cosmology/cosmolib.h
esutil/cosmology/cosmolib_pywrap.c
esutil/cosmology/cosmology.py
esutil/cosmology/__pycache__/__init__.cpython-310.pyc
esutil/cosmology/__pycache__/__init__.cpython-311.pyc
esutil/cosmology/__pycache__/__init__.cpython-312.pyc
esutil/cosmology/__pycache__/cosmology.cpython-310.pyc
esutil/cosmology/__pycache__/cosmology.cpython-311.pyc
esutil/cosmology/__pycache__/cosmology.cpython-312.pyc
esutil/htm/__init__.py
esutil/htm/_htmc.cpython-310-x86_64-linux-gnu.so
esutil/htm/_htmc.cpython-311-x86_64-linux-gnu.so
esutil/htm/_htmc.cpython-312-x86_64-linux-gnu.so
esutil/htm/htm.py
esutil/htm/htmc.cc
esutil/htm/htmc.h
esutil/htm/htmc.i
esutil/htm/htmc.py
esutil/htm/htmc_wrap-backup.cc
esutil/htm/htmc_wrap.cc
esutil/htm/runswig.sh
esutil/htm/__pycache__/__init__.cpython-310.pyc
esutil/htm/__pycache__/__init__.cpython-311.pyc
esutil/htm/__pycache__/__init__.cpython-312.pyc
esutil/htm/__pycache__/htm.cpython-310.pyc
esutil/htm/__pycache__/htm.cpython-311.pyc
esutil/htm/__pycache__/htm.cpython-312.pyc
esutil/htm/__pycache__/htmc.cpython-310.pyc
esutil/htm/__pycache__/htmc.cpython-311.pyc
esutil/htm/__pycache__/htmc.cpython-312.pyc
esutil/htm/htm_src/BitList.cpp
esutil/htm/htm_src/BitList.h
esutil/htm/htm_src/BitList.hxx
esutil/htm/htm_src/SConscript
